{
	"configurations" : 
	[
		{
			"directories" : 
			[
				{
					"build" : ".",
					"hasInstallRule" : true,
					"jsonFile" : "directory-.-6eb9d7bb025a2e9771ea.json",
					"minimumCMakeVersion" : 
					{
						"string" : "3.12"
					},
					"projectIndex" : 0,
					"source" : ".",
					"targetIndexes" : 
					[
						0,
						1
					]
				}
			],
			"name" : "",
			"projects" : 
			[
				{
					"directoryIndexes" : 
					[
						0
					],
					"name" : "lerobot_so100",
					"targetIndexes" : 
					[
						0,
						1
					]
				}
			],
			"targets" : 
			[
				{
					"directoryIndex" : 0,
					"id" : "lerobot_so100_uninstall::@6890427a1f51a3e7e1df",
					"jsonFile" : "target-lerobot_so100_uninstall-9ad4f9ab2d5a974e129d.json",
					"name" : "lerobot_so100_uninstall",
					"projectIndex" : 0
				},
				{
					"directoryIndex" : 0,
					"id" : "uninstall::@6890427a1f51a3e7e1df",
					"jsonFile" : "target-uninstall-d698cf0743d3d69169d7.json",
					"name" : "uninstall",
					"projectIndex" : 0
				}
			]
		}
	],
	"kind" : "codemodel",
	"paths" : 
	{
		"build" : "/home/kabilankb/isaac_lerobot_new/build/lerobot_so100",
		"source" : "/home/kabilankb/isaac_lerobot_new/src/lerobot_so100"
	},
	"version" : 
	{
		"major" : 2,
		"minor" : 3
	}
}
